cargame/__init__.py
cargame/runner.py
cargame/bin/car_game_linux
cargame/bin/car_game_windows.exe
cargame-2.2.0.dist-info/licenses/LICENSE
cargame-2.2.0.dist-info/METADATA
cargame-2.2.0.dist-info/WHEEL
cargame-2.2.0.dist-info/entry_points.txt
cargame-2.2.0.dist-info/top_level.txt
cargame-2.2.0.dist-info/RECORD
