Metadata-Version: 2.4
Name: cargame
Version: 2.2.0
Summary: Terminal car racing game with multiplayer and lobby
Project-URL: Homepage, https://github.com/ASWINa1636/Car-game-publish-setup
Project-URL: Source, https://github.com/ASWINa1636/Car-game-publish-setup
Project-URL: Issues, https://github.com/ASWINa1636/Car-game-publish-setup
Requires-Python: >=3.8
License-File: LICENSE
Dynamic: license-file
